MANIFEST.in
setup.py
flask_error/__init__.py
flask_error.egg-info/PKG-INFO
flask_error.egg-info/SOURCES.txt
flask_error.egg-info/dependency_links.txt
flask_error.egg-info/not-zip-safe
flask_error.egg-info/top_level.txt