Metadata-Version: 1.0
Name: flask-error
Version: 0.1
Summary: A simple and extensible way of displaying error messages.
Home-page: http://github.com/pgallen90/flask_error
Author: Patrick Allen
Author-email: patrickgallen@gmail.com
License: MIT
Platform: UNKNOWN
